airflow/providers/common/messaging/__init__.py
airflow/providers/common/messaging/get_provider_info.py
airflow/providers/common/messaging/providers/__init__.py
airflow/providers/common/messaging/providers/base_provider.py
airflow/providers/common/messaging/triggers/__init__.py
airflow/providers/common/messaging/triggers/msg_queue.py
apache_airflow_providers_common_messaging-2.0.2.dist-info/entry_points.txt
apache_airflow_providers_common_messaging-2.0.2.dist-info/licenses/LICENSE
apache_airflow_providers_common_messaging-2.0.2.dist-info/licenses/NOTICE
apache_airflow_providers_common_messaging-2.0.2.dist-info/WHEEL
apache_airflow_providers_common_messaging-2.0.2.dist-info/METADATA
apache_airflow_providers_common_messaging-2.0.2.dist-info/RECORD
